[
    {
        "File Name": "invoice-rekening-listrik-511444207243-202606-.pdf",
        "ID Pelanggan": "511444207243",
        "Nama Pelanggan": "KOLAM RENANG UNESA",
        "Gol": "S1",
        "Tarif": "105000VA",
        "Total Tagihan": 16731900,
        "kWh LWBP": 18591,
        "Tarif LWBP": 900.0,
        "kWh WBP": 0,
        "Tarif WBP": 0.0,
        "kVArh": 0,
        "Tarif kVArh": 0.0
    },
    {
        "File Name": "invoice-rekening-listrik-511607257577-202606-.pdf",
        "ID Pelanggan": "511607257577",
        "Nama Pelanggan": "ASRAMA UNESA",
        "Gol": "P1",
        "Tarif": "197000VA",
        "Total Tagihan": 21373289,
        "kWh LWBP": 12576,
        "Tarif LWBP": 1699.53,
        "kWh WBP": 0,
        "Tarif WBP": 0.0,
        "kVArh": 0,
        "Tarif kVArh": 0.0
    },
    {
        "File Name": "invoice-rekening-listrik-511620052962-202606-.pdf",
        "ID Pelanggan": "511620052962",
        "Nama Pelanggan": "PPG UNESA",
        "Gol": "S2",
        "Tarif": "690000VA",
        "Total Tagihan": 31137908,
        "kWh LWBP": 34818,
        "Tarif LWBP": 735.0,
        "kWh WBP": 5031,
        "Tarif WBP": 1102.5,
        "kVArh": 0,
        "Tarif kVArh": 925.0
    },
    {
        "File Name": "invoice-rekening-listrik-511620087202-202606-.pdf",
        "ID Pelanggan": "511620087202",
        "Nama Pelanggan": "SPORT SCIENCE",
        "Gol": "S1",
        "Tarif": "197000VA",
        "Total Tagihan": 7103700,
        "kWh LWBP": 7893,
        "Tarif LWBP": 900.0,
        "kWh WBP": 0,
        "Tarif WBP": 0.0,
        "kVArh": 0,
        "Tarif kVArh": 0.0
    },
    {
        "File Name": "invoice-rekening-listrik-511620087210-202606-.pdf",
        "ID Pelanggan": "511620087210",
        "Nama Pelanggan": "SMP LABORATORIUM UNESA",
        "Gol": "S2",
        "Tarif": "555000VA",
        "Total Tagihan": 22979775,
        "kWh LWBP": 27914,
        "Tarif LWBP": 735.0,
        "kWh WBP": 2234,
        "Tarif WBP": 1102.5,
        "kVArh": 0,
        "Tarif kVArh": 925.0
    },
    {
        "File Name": "invoice-rekening-listrik-511620126643-202606-.pdf",
        "ID Pelanggan": "511620126643",
        "Nama Pelanggan": "UNESA GED PENDIDIKAN",
        "Gol": "S2",
        "Tarif": "1110000VA",
        "Total Tagihan": 104376615,
        "kWh LWBP": 118102,
        "Tarif LWBP": 735.0,
        "kWh WBP": 15938,
        "Tarif WBP": 1102.5,
        "kVArh": 0,
        "Tarif kVArh": 925.0
    },
    {
        "File Name": "invoice-rekening-listrik-511620212158-202606-.pdf",
        "ID Pelanggan": "511620212158",
        "Nama Pelanggan": "ASRAMA PUTRI 1 UNESA",
        "Gol": "B2",
        "Tarif": "147000VA",
        "Total Tagihan": 34396862,
        "kWh LWBP": 23809,
        "Tarif LWBP": 1444.7,
        "kWh WBP": 0,
        "Tarif WBP": 0.0,
        "kVArh": 0,
        "Tarif kVArh": 0.0
    },
    {
        "File Name": "invoice-rekening-listrik-511620212190-202606-.pdf",
        "ID Pelanggan": "511620212190",
        "Nama Pelanggan": "ASRAMA PUTRI 2 UNESA",
        "Gol": "B2",
        "Tarif": "147000VA",
        "Total Tagihan": 11849429,
        "kWh LWBP": 8202,
        "Tarif LWBP": 1444.7,
        "kWh WBP": 0,
        "Tarif WBP": 0.0,
        "kVArh": 0,
        "Tarif kVArh": 0.0
    },
    {
        "File Name": "invoice-rekening-listrik-511620219736-202606-.pdf",
        "ID Pelanggan": "511620219736",
        "Nama Pelanggan": "GEDUNG FUTSAL UNESA",
        "Gol": "B2",
        "Tarif": "164000VA",
        "Total Tagihan": 22596553,
        "kWh LWBP": 15641,
        "Tarif LWBP": 1444.7,
        "kWh WBP": 0,
        "Tarif WBP": 0.0,
        "kVArh": 0,
        "Tarif kVArh": 0.0
    },
    {
        "File Name": "invoice-rekening-listrik-511620304933-202606-.pdf",
        "ID Pelanggan": "511620304933",
        "Nama Pelanggan": "GEDUNG CPD UNESA",
        "Gol": "S2",
        "Tarif": "865000VA",
        "Total Tagihan": 69168278,
        "kWh LWBP": 76957,
        "Tarif LWBP": 735.0,
        "kWh WBP": 11433,
        "Tarif WBP": 1102.5,
        "kVArh": 0,
        "Tarif kVArh": 925.0
    },
    {
        "File Name": "invoice-rekening-listrik-511620304958-202606-.pdf",
        "ID Pelanggan": "511620304958",
        "Nama Pelanggan": "GEDUNG FAK. SENI UNESA",
        "Gol": "S2",
        "Tarif": "555000VA",
        "Total Tagihan": 24786773,
        "kWh LWBP": 28625,
        "Tarif LWBP": 735.0,
        "kWh WBP": 3399,
        "Tarif WBP": 1102.5,
        "kVArh": 0,
        "Tarif kVArh": 925.0
    },
    {
        "File Name": "invoice-rekening-listrik-511620304966-202606-.pdf",
        "ID Pelanggan": "511620304966",
        "Nama Pelanggan": "GEDUNG PERPUSTAKAAN UNESA",
        "Gol": "S2",
        "Tarif": "345000VA",
        "Total Tagihan": 35415240,
        "kWh LWBP": 39595,
        "Tarif LWBP": 735.0,
        "kWh WBP": 5726,
        "Tarif WBP": 1102.5,
        "kVArh": 0,
        "Tarif kVArh": 925.0
    },
    {
        "File Name": "invoice-rekening-listrik-511620345574-202606-.pdf",
        "ID Pelanggan": "511620345574",
        "Nama Pelanggan": "GEDUNG BASKET INDOOR",
        "Gol": "S1",
        "Tarif": "41500VA",
        "Total Tagihan": 7420500,
        "kWh LWBP": 8245,
        "Tarif LWBP": 900.0,
        "kWh WBP": 0,
        "Tarif WBP": 0.0,
        "kVArh": 0,
        "Tarif kVArh": 0.0
    },
    {
        "File Name": "invoice-rekening-listrik-511620378473-202606-.pdf",
        "ID Pelanggan": "511620378473",
        "Nama Pelanggan": "RUSUN UNESA SURABAYA",
        "Gol": "S1",
        "Tarif": "197000VA",
        "Total Tagihan": 15625800,
        "kWh LWBP": 17362,
        "Tarif LWBP": 900.0,
        "kWh WBP": 0,
        "Tarif WBP": 0.0,
        "kVArh": 0,
        "Tarif kVArh": 0.0
    },
    {
        "File Name": "invoice-rekening-listrik-511620405543-202606-.pdf",
        "ID Pelanggan": "511620405543",
        "Nama Pelanggan": "LAB ANTI DOPPING UNESA",
        "Gol": "S2",
        "Tarif": "555000VA",
        "Total Tagihan": 24745773,
        "kWh LWBP": 21453,
        "Tarif LWBP": 735.0,
        "kWh WBP": 2917,
        "Tarif WBP": 1102.5,
        "kVArh": 6229,
        "Tarif kVArh": 925.0
    },
    {
        "File Name": "invoice-rekening-listrik-511620435955-202606-.pdf",
        "ID Pelanggan": "511620435955",
        "Nama Pelanggan": "GEDUNG PSIKOLOGI UNESA",
        "Gol": "S2",
        "Tarif": "555000VA",
        "Total Tagihan": 27695535,
        "kWh LWBP": 32512,
        "Tarif LWBP": 735.0,
        "kWh WBP": 3446,
        "Tarif WBP": 1102.5,
        "kVArh": 0,
        "Tarif kVArh": 925.0
    },
    {
        "File Name": "invoice-rekening-listrik-511620438389-202606-.pdf",
        "ID Pelanggan": "511620438389",
        "Nama Pelanggan": "G KULIAH BRSM OR DAN KES",
        "Gol": "S1",
        "Tarif": "197000VA",
        "Total Tagihan": 13170600,
        "kWh LWBP": 14634,
        "Tarif LWBP": 900.0,
        "kWh WBP": 0,
        "Tarif WBP": 0.0,
        "kVArh": 0,
        "Tarif kVArh": 0.0
    },
    {
        "File Name": "invoice-rekening-listrik-511620446071-202606-.pdf",
        "ID Pelanggan": "511620446071",
        "Nama Pelanggan": "FIKK GEDUNG U1/U2",
        "Gol": "S1",
        "Tarif": "197000VA",
        "Total Tagihan": 44735400,
        "kWh LWBP": 49706,
        "Tarif LWBP": 900.0,
        "kWh WBP": 0,
        "Tarif WBP": 0.0,
        "kVArh": 0,
        "Tarif kVArh": 0.0
    },
    {
        "File Name": "invoice-rekening-listrik-511620472469-202606-.pdf",
        "ID Pelanggan": "511620472469",
        "Nama Pelanggan": "GEDUNG SAWUNGGALING UNESA",
        "Gol": "S1",
        "Tarif": "197000VA",
        "Total Tagihan": 13773600,
        "kWh LWBP": 15304,
        "Tarif LWBP": 900.0,
        "kWh WBP": 0,
        "Tarif WBP": 0.0,
        "kVArh": 0,
        "Tarif kVArh": 0.0
    }
]